README.md
grape_pi.py
main.py
src/__init__.py
src/custom_graphgym/__init__.py
src/custom_graphgym/act/__init__.py
src/custom_graphgym/act/example.py
src/custom_graphgym/act/none.py
src/custom_graphgym/config/__init__.py
src/custom_graphgym/config/example.py
src/custom_graphgym/config/grape_pi.py
src/custom_graphgym/encoder/__init__.py
src/custom_graphgym/encoder/example.py
src/custom_graphgym/head/__init__.py
src/custom_graphgym/head/example.py
src/custom_graphgym/head/protein.py
src/custom_graphgym/layer/__init__.py
src/custom_graphgym/layer/example.py
src/custom_graphgym/layer/gcnconv_with_edgeweight.py
src/custom_graphgym/loader/__init__.py
src/custom_graphgym/loader/example.py
src/custom_graphgym/loader/protein.py
src/custom_graphgym/logger.py
src/custom_graphgym/loss/__init__.py
src/custom_graphgym/loss/example.py
src/custom_graphgym/loss/protein.py
"src/custom_graphgym/metrics/__init__,py.py"
src/custom_graphgym/metrics/grape_pi.py
src/custom_graphgym/network/__init__.py
src/custom_graphgym/network/example.py
src/custom_graphgym/optimizer/__init__.py
src/custom_graphgym/optimizer/example.py
src/custom_graphgym/pooling/__init__.py
src/custom_graphgym/pooling/example.py
src/custom_graphgym/stage/__init__.py
src/custom_graphgym/stage/example.py
src/custom_graphgym/train/__init__.py
src/custom_graphgym/train/example.py
src/custom_graphgym/train/gcnconv_model_builder.py
src/custom_graphgym/train/graphsage_model_builder.py
src/custom_graphgym/transform/__init__.py
src/utils/__init__.py
src/utils/agg_batch.py
src/utils/best_model.py
src/utils/config.py
src/utils/configs_gen.py
src/utils/train.py
grape_pi-1.0.2.dist-info/METADATA
grape_pi-1.0.2.dist-info/WHEEL
grape_pi-1.0.2.dist-info/entry_points.txt
grape_pi-1.0.2.dist-info/RECORD
