Metadata-Version: 2.1
Name: grape-pi
Version: 1.0.2
Summary: Using graph neural networks to enhance protein identification using protein interaction networks.
Author: Chunhui Gu
Author-email: fduguchunhui@gmail.com
Requires-Python: >=3.11.0,<=3.12.0
Classifier: Programming Language :: Python :: 3
Classifier: Programming Language :: Python :: 3.11
Classifier: Programming Language :: Python :: 3.12
Provides-Extra: bruker
Provides-Extra: notebooks
Requires-Dist: chardet (>=5.2.0,<6.0.0)
Requires-Dist: gseapy (>=1.1.3,<2.0.0) ; extra == "notebooks"
Requires-Dist: h5py (>=3.11.0,<4.0.0)
Requires-Dist: hydra-core (>=1.3.2,<2.0.0)
Requires-Dist: jupyter (>=1.1.1,<2.0.0) ; extra == "notebooks"
Requires-Dist: matplotlib (>=3.9.0,<4.0.0) ; extra == "notebooks"
Requires-Dist: matplotlib-venn (>=1.1.1,<2.0.0) ; extra == "notebooks"
Requires-Dist: numpy (>=1.26.4,<2.0.0)
Requires-Dist: ogb (>=1.3.6,<2.0.0)
Requires-Dist: openpyxl (>=3.1.5,<4.0.0) ; extra == "bruker"
Requires-Dist: overrides (>=7.7.0,<8.0.0)
Requires-Dist: pandas (>=2.2.2,<3.0.0)
Requires-Dist: psutil (>=5.9.8,<6.0.0)
Requires-Dist: pyparsing (>=3.1.2,<4.0.0)
Requires-Dist: pytorch-lightning (>=2.2.5,<3.0.0)
Requires-Dist: qtconsole (>=5.6.1,<6.0.0) ; extra == "notebooks"
Requires-Dist: seaborn (==0.12.0) ; extra == "notebooks"
Requires-Dist: tensorboardx (>=2.6.2.2,<3.0.0.0)
Requires-Dist: torch (==2.4.0)
Requires-Dist: torch-geometric (>=2.6.1,<3.0.0)
Requires-Dist: yacs (>=0.1.8,<0.2.0)
